faker_ecommerce/__init__.py
faker_ecommerce/provider.py
faker_ecommerce_provider-1.0.2.dist-info/licenses/LICENSE
tests/test_provider.py
faker_ecommerce_provider-1.0.2.dist-info/METADATA
faker_ecommerce_provider-1.0.2.dist-info/WHEEL
faker_ecommerce_provider-1.0.2.dist-info/top_level.txt
faker_ecommerce_provider-1.0.2.dist-info/RECORD
