Metadata-Version: 2.4
Name: faker-ecommerce-provider
Version: 1.0.2
Summary: Generate realistic e-commerce test data: products, SKUs, orders, 20+ carriers, 20+ payment methods, coupons, reviews, and more
License: MIT
Project-URL: Homepage, https://github.com/rodrigobnogueira/faker-ecommerce
Project-URL: Repository, https://github.com/rodrigobnogueira/faker-ecommerce
Keywords: faker,ecommerce,e-commerce,fake-data,testing,shopping
Classifier: Development Status :: 4 - Beta
Classifier: Intended Audience :: Developers
Classifier: License :: OSI Approved :: MIT License
Classifier: Programming Language :: Python :: 3
Classifier: Programming Language :: Python :: 3.10
Classifier: Programming Language :: Python :: 3.11
Classifier: Programming Language :: Python :: 3.12
Classifier: Programming Language :: Python :: 3.13
Requires-Python: >=3.10
License-File: LICENSE
Requires-Dist: faker>=18.0.0
Dynamic: license-file
